{
  "mdx_path": "app/content/interactions-insulin-glargine/with-finasteride.mdx",
  "topic": "interactions-insulin-glargine",
  "slug": "with-finasteride",
  "title_hint": "Lantus + finasteride: interaction profile",
  "primary_query": "lantus and finasteride interaction",
  "author_slug": "maya-okafor-md",
  "reviewer_slug": "elena-vasquez-md",
  "guardrails": {
    "word_count": 3813,
    "sentence_stddev": 33.21,
    "citations_per_200w": 1.63,
    "passed": true
  },
  "queued_at": 1781930010.8465614,
  "status": "awaiting_clinician_review"
}