{
  "mdx_path": "app/content/pregnancy-fezolinetant/pregnancy.mdx",
  "topic": "pregnancy-fezolinetant",
  "slug": "pregnancy",
  "title_hint": "Veozah during pregnancy: safety guide",
  "primary_query": "is Veozah safe during pregnancy",
  "author_slug": "elena-vasquez-md",
  "reviewer_slug": "elena-vasquez-md",
  "guardrails": {
    "word_count": 3301,
    "sentence_stddev": 19.07,
    "citations_per_200w": 1.64,
    "passed": true
  },
  "queued_at": 1781929980.638956,
  "status": "awaiting_clinician_review"
}